unibase/__init__.py
unibase/cli.py
unibase/config.py
unibase/generate_pdf.py
unibase/registry.py
unibase/db/__init__.py
unibase/db/base.py
unibase/db/graph.py
unibase/db/image.py
unibase/db/multimodal.py
unibase/db/nosql.py
unibase/db/sql.py
unibase/db/vector.py
unibase/utils/__init__.py
unibase/utils/ai_agent.py
unibase/utils/error_handling.py
unibase/utils/etl.py
unibase/utils/groq_integration.py
unibase/utils/logger.py
unibase-0.1.2.dist-info/licenses/LICENSE
unibase-0.1.2.dist-info/METADATA
unibase-0.1.2.dist-info/WHEEL
unibase-0.1.2.dist-info/entry_points.txt
unibase-0.1.2.dist-info/top_level.txt
unibase-0.1.2.dist-info/RECORD
