Metadata-Version: 2.4
Name: unibase
Version: 0.1.2
Summary: UNIBASE: The Unified AI-Powered Database CLI to manage SQL, NoSQL, Graph, Vector, Image, and Multi-modal databases
Author-email: Dhruv Dawar <dhruvdawar11022006@gmail.com>
License: MIT
Keywords: database,ai,cli,sql,nosql,graph,vector,unified
Classifier: Development Status :: 4 - Beta
Classifier: Intended Audience :: Developers
Classifier: License :: OSI Approved :: MIT License
Classifier: Programming Language :: Python :: 3
Classifier: Programming Language :: Python :: 3.8
Classifier: Topic :: Database
Classifier: Topic :: Utilities
Classifier: Environment :: Console
Requires-Python: >=3.8
License-File: LICENSE
Requires-Dist: typer[all]>=0.9.0
Requires-Dist: fpdf2>=2.5
Requires-Dist: tabulate
Requires-Dist: networkx
Requires-Dist: matplotlib
Requires-Dist: pymongo
Requires-Dist: psycopg2-binary
Requires-Dist: mysql-connector-python
Requires-Dist: boto3
Requires-Dist: pandas
Requires-Dist: openai
Dynamic: license-file
